terminarty/BoxStyles.py
terminarty/__init__.py
terminarty/box.py
terminarty/cursor.py
terminarty/getchar.py
terminarty/progressbar.py
terminarty/terminal.py
terminarty/waiting.py
terminarty-1.0.0.dist-info/LICENSE
terminarty-1.0.0.dist-info/METADATA
terminarty-1.0.0.dist-info/WHEEL
terminarty-1.0.0.dist-info/top_level.txt
terminarty-1.0.0.dist-info/RECORD
